congreso/__init__.py
congreso/congreso.py
congreso-1.0.4.dist-info/METADATA
congreso-1.0.4.dist-info/WHEEL
congreso-1.0.4.dist-info/licenses/LICENSE
congreso-1.0.4.dist-info/RECORD
