Metadata-Version: 2.3
Name: congreso
Version: 1.0.4
Summary: A Python library containing document processing functions
Author-email: Paula Mateos Marin <paulamateosm@gmail.com>, Jesus Cerquide Bueno <cerquide@iiia.csic.es>
License: MIT License
License-File: LICENSE
Classifier: License :: OSI Approved :: MIT License
Classifier: Operating System :: OS Independent
Classifier: Programming Language :: Python :: 3
Requires-Python: >=3.8
